cspot/__init__.py
cspot/addPredictions.py
cspot/archives/gator-01272023.py
cspot/archives/toolbox-02032023/ftools.py
cspot/archives/toolbox-02032023/GPUselect.py
cspot/archives/toolbox-02032023/imtools.py
cspot/archives/toolbox-02032023/PartitionOfImage.py
cspot/archives/toolbox-02032023/PartitionOfImageOM.py
cspot/archives/toolbox-02032023/toolbox.py
cspot/archives/UNet-02032023.py
cspot/cloneFolder.py
cspot/csExport.py
cspot/csObject.py
cspot/csPhenotype.py
cspot/csPipeline.py
cspot/cspot.py
cspot/csPredict.py
cspot/csTrain.py
cspot/generateCSScore.py
cspot/generateThumbnails.py
cspot/generateTrainTestSplit.py
cspot/mergecsObject.py
cspot/scatterPlot.py
cspot/toolbox/__init__.py
cspot/toolbox/ftools.py
cspot/toolbox/GPUselect.py
cspot/toolbox/imtools.py
cspot/toolbox/PartitionOfImage.py
cspot/UNet.py
cspot-1.2.0.dist-info/METADATA
cspot-1.2.0.dist-info/WHEEL
cspot-1.2.0.dist-info/RECORD
